eloope/__init__.py
eloope/command.py
eloope/controller.py
eloope/engine.py
eloope/logger.py
eloope/main.py
eloope/manager.py
eloope/server.py
eloope/service_pb2.py
eloope/service_pb2_grpc.py
eloope/setting.py
eloope-2019.6.8.dist-info/LICENSE
eloope-2019.6.8.dist-info/METADATA
eloope-2019.6.8.dist-info/WHEEL
eloope-2019.6.8.dist-info/entry_points.txt
eloope-2019.6.8.dist-info/top_level.txt
eloope-2019.6.8.dist-info/RECORD
