Metadata-Version: 2.1
Name: eloope
Version: 2019.6.8
Summary: Event loop engine.
Home-page: https://github.com/Czw96/eloope
Author: Czw
Author-email: 459749926@qq.com
License: UNKNOWN
Platform: UNKNOWN
Classifier: Programming Language :: Python :: 3
Classifier: License :: OSI Approved :: MIT License
Classifier: Operating System :: OS Independent
Requires-Dist: gevent
Requires-Dist: requests
Requires-Dist: toolset
